README.md
setup.cfg
setup.py
edbo/__init__.py
edbo/acq_func.py
edbo/base_models.py
edbo/bro.py
edbo/chem_utils.py
edbo/encode.py
edbo/feature_selection.py
edbo/feature_utils.py
edbo/init_scheme.py
edbo/math_utils.py
edbo/models.py
edbo/objective.py
edbo/opt_utils.py
edbo/pd_utils.py
edbo/plot_utils.py
edbo/torch_utils.py
edbo/utils.py
edbo.egg-info/PKG-INFO
edbo.egg-info/SOURCES.txt
edbo.egg-info/dependency_links.txt
edbo.egg-info/requires.txt
edbo.egg-info/top_level.txt