Metadata-Version: 1.1
Name: edbo
Version: 0.1.0
Summary: Experimental design via Bayesian optimization
Home-page: https://github.com/b-shields/edbo
Author: Benjamin J. Shields
Author-email: shields.benjamin.j@gmail.com
License: MIT
Download-URL: https://github.com/b-shields/edbo/archive/edbo.tar.gz
Keywords: Bayesian Optimization,Chemical Reaction Optimization
Platform: UNKNOWN
Classifier: Development Status :: 3 - Alpha
Classifier: Intended Audience :: Science/Research
Classifier: Topic :: Scientific/Engineering :: Chemistry
Classifier: License :: OSI Approved :: MIT License
Classifier: Programming Language :: Python :: 3.7
